CHANGELOG
LICENSE
MANIFEST.in
README.md
WAIVER
WAIVER.asc
requirements.txt
setup.cfg
setup.py
test_requirements.txt
eth_monitor/callback.py
eth_monitor/chain.py
eth_monitor/config.py
eth_monitor/error.py
eth_monitor/index.py
eth_monitor/rules.py
eth_monitor/run.py
eth_monitor/settings.py
eth_monitor.egg-info/PKG-INFO
eth_monitor.egg-info/SOURCES.txt
eth_monitor.egg-info/dependency_links.txt
eth_monitor.egg-info/entry_points.txt
eth_monitor.egg-info/requires.txt
eth_monitor.egg-info/top_level.txt
eth_monitor/cli/__init__.py
eth_monitor/cli/arg.py
eth_monitor/cli/config.py
eth_monitor/cli/log.py
eth_monitor/cli/rules.py
eth_monitor/data/config/cache.ini
eth_monitor/data/config/filter.ini
eth_monitor/data/config/monitor.ini
eth_monitor/data/config/renderer.ini
eth_monitor/filters/__init__.py
eth_monitor/filters/base.py
eth_monitor/filters/block.py
eth_monitor/filters/cache.py
eth_monitor/filters/out.py
eth_monitor/filters/run.py
eth_monitor/importers/etherscan.py
eth_monitor/mock/filter_plain.py
eth_monitor/mock/filter_ruled.py
eth_monitor/runnable/import.py
eth_monitor/runnable/list.py
eth_monitor/runnable/sync.py
eth_monitor/runnable/sync_thread_range.py
man/build/eth-monitor-import.1
man/build/eth-monitor-list.1
man/build/eth-monitor-sync.1
man/build/eth-monitor.1
tests/test_basic.py