Metadata-Version: 2.1
Name: eth-monitor
Version: 0.8.9
Summary: Monitor and cache transactions using match filters
Home-page: https://git.defalsify.org/eth-monitor
Author: Louis Holbrook
Author-email: dev@holbrook.no
License: AGPLv3+
Keywords: dlt,blockchain,cryptocurrency,ethereum
Classifier: Programming Language :: Python :: 3
Classifier: Operating System :: OS Independent
Classifier: Development Status :: 3 - Alpha
Classifier: Topic :: Software Development :: Libraries
Classifier: Environment :: Console
Classifier: Intended Audience :: Developers
Classifier: License :: OSI Approved :: GNU Affero General Public License v3 or later (AGPLv3+)
Classifier: Topic :: Internet
Requires-Python: >=3.8
License-File: LICENSE
Requires-Dist: chainlib-eth~=0.6.0
Requires-Dist: chainlib~=0.5.2
Requires-Dist: chainsyncer~=0.8.5
Requires-Dist: leveldir~=0.3.0
Requires-Dist: eth-cache~=0.4.0
Requires-Dist: confini~=0.6.3
